type_checker/decorators.py
type_checker_decorators-0.1.3.dist-info/METADATA
type_checker_decorators-0.1.3.dist-info/WHEEL
type_checker_decorators-0.1.3.dist-info/RECORD
