Metadata-Version: 2.1
Name: type-checker-decorators
Version: 0.1.3
Summary: 
Author: Aboussejra
Author-email: Amir.Boussejra@viavisolutions.com
Requires-Python: >=3.7
Classifier: Programming Language :: Python :: 3
Classifier: Programming Language :: Python :: 3.7
Classifier: Programming Language :: Python :: 3.8
Classifier: Programming Language :: Python :: 3.9
Classifier: Programming Language :: Python :: 3.10
Classifier: Programming Language :: Python :: 3.11
